[
  {
    "name": "Sweet Bonanza",
    "slug": "sweet-bonanza",
    "description": null,
    "url": "https://slotslaunch.com/iframe/5483",
    "thumb": "https://assets.slotslaunch.com/5706/sweet-bonanza.jpg",
    "ProviderName": "Pragmatic Play",
    "ProviderImage": "https://assets.slotslaunch.com/15981/pragmatic-play.png",
    "TypeName": "Slots",
    "ThemeName": null,
    "megaways": 0,
    "bonus_buy": 1,
    "progressive": 0,
    "featured": 0,
    "release": "",
    "reels": "6",
    "rtp": "96.51",
    "volatility": "4",
    "paylines": "Fixed",
    "created_at": "2022-01-02T03:13:28.000000Z",
    "updated_at": "2026-01-14T17:23:40.000000Z",
    "published": 1,
    "provider_id": 161,
    "franchise": "Sweet Bonanza"
  },
  {
    "name": "Sweet Bonanza 1000",
    "slug": "sweet-bonanza-1000",
    "description": null,
    "url": "https://slotslaunch.com/iframe/23537",
    "thumb": "https://assets.slotslaunch.com/23735/sweet-bonanza-1000.jpg",
    "ProviderName": "Pragmatic Play",
    "ProviderImage": "https://assets.slotslaunch.com/15981/pragmatic-play.png",
    "TypeName": "Slots",
    "ThemeName": null,
    "megaways": 0,
    "bonus_buy": 1,
    "progressive": 0,
    "featured": 0,
    "release": "",
    "reels": "6",
    "rtp": "96.53",
    "volatility": "",
    "paylines": "Fixed",
    "created_at": "2024-05-03T03:48:40.000000Z",
    "updated_at": "2026-01-14T17:23:40.000000Z",
    "published": 1,
    "provider_id": 161,
    "franchise": "Sweet Bonanza"
  },
  {
    "name": "Sweet Bonanza Dice",
    "slug": "sweet-bonanza-dice",
    "description": null,
    "url": "https://slotslaunch.com/iframe/5484",
    "thumb": "https://assets.slotslaunch.com/5707/sweet-bonanza-dice.jpg",
    "ProviderName": "Pragmatic Play",
    "ProviderImage": "https://assets.slotslaunch.com/15981/pragmatic-play.png",
    "TypeName": "Slots",
    "ThemeName": null,
    "megaways": 0,
    "bonus_buy": 0,
    "progressive": 0,
    "featured": 0,
    "release": "",
    "reels": "",
    "rtp": "",
    "volatility": "",
    "paylines": "",
    "created_at": "2022-01-02T03:13:28.000000Z",
    "updated_at": "2026-01-15T22:45:33.000000Z",
    "published": 1,
    "provider_id": 161,
    "franchise": "Sweet Bonanza"
  },
  {
    "name": "Gates of Olympus",
    "slug": "gates-of-olympus",
    "description": null,
    "url": "https://slotslaunch.com/iframe/5397",
    "thumb": "https://assets.slotslaunch.com/5621/gates-of-olympus.jpg",
    "ProviderName": "Pragmatic Play",
    "ProviderImage": "https://assets.slotslaunch.com/15981/pragmatic-play.png",
    "TypeName": "Slots",
    "ThemeName": null,
    "megaways": 0,
    "bonus_buy": 0,
    "progressive": 0,
    "featured": 0,
    "release": "",
    "reels": "6",
    "rtp": "",
    "volatility": "",
    "paylines": "Fixed",
    "created_at": "2022-01-02T03:13:28.000000Z",
    "updated_at": "2026-01-14T17:23:40.000000Z",
    "published": 1,
    "provider_id": 161,
    "franchise": "Gates of Olympus"
  },
  {
    "name": "Gates of Olympus 1000",
    "slug": "gates-of-olympus-1000",
    "description": null,
    "url": "https://slotslaunch.com/iframe/16716",
    "thumb": "https://assets.slotslaunch.com/18440/gates-of-olympus-1000.jpg",
    "ProviderName": "Pragmatic Play",
    "ProviderImage": "https://assets.slotslaunch.com/15981/pragmatic-play.png",
    "TypeName": "Slots",
    "ThemeName": null,
    "megaways": 0,
    "bonus_buy": 0,
    "progressive": 0,
    "featured": 0,
    "release": "",
    "reels": "6",
    "rtp": "",
    "volatility": "",
    "paylines": "Fixed",
    "created_at": "2023-11-09T00:29:05.000000Z",
    "updated_at": "2026-01-14T17:23:40.000000Z",
    "published": 1,
    "provider_id": 161,
    "franchise": "Gates of Olympus"
  },
  {
    "name": "Gates of Gatot Kaca",
    "slug": "gates-of-gatot-kaca",
    "description": null,
    "url": "https://slotslaunch.com/iframe/4078",
    "thumb": "https://assets.slotslaunch.com/3490/gates-of-gatot-kaca.jpg",
    "ProviderName": "Pragmatic Play",
    "ProviderImage": "https://assets.slotslaunch.com/15981/pragmatic-play.png",
    "TypeName": "Slots",
    "ThemeName": null,
    "megaways": 0,
    "bonus_buy": 0,
    "progressive": 0,
    "featured": 0,
    "release": "",
    "reels": "",
    "rtp": "",
    "volatility": "",
    "paylines": "",
    "created_at": "2022-12-15T01:33:54.000000Z",
    "updated_at": "2025-10-02T16:53:15.000000Z",
    "published": 1,
    "provider_id": 161,
    "franchise": "Gates of Olympus"
  },
  {
    "name": "Big Bass Bonanza",
    "slug": "big-bass-bonanza",
    "description": null,
    "url": "https://slotslaunch.com/iframe/5356",
    "thumb": "https://assets.slotslaunch.com/5580/big-bass-bonanza.jpg",
    "ProviderName": "Pragmatic Play",
    "ProviderImage": "https://assets.slotslaunch.com/15981/pragmatic-play.png",
    "TypeName": "Slots",
    "ThemeName": "Fish",
    "megaways": 0,
    "bonus_buy": 0,
    "progressive": 0,
    "featured": 0,
    "release": "",
    "reels": "5",
    "rtp": "",
    "volatility": "",
    "paylines": "Fixed",
    "created_at": "2022-01-02T03:13:28.000000Z",
    "updated_at": "2026-01-14T17:23:41.000000Z",
    "published": 1,
    "provider_id": 161,
    "franchise": "Big Bass"
  },
  {
    "name": "Big Bass Splash",
    "slug": "big-bass-splash",
    "description": null,
    "url": "https://slotslaunch.com/iframe/742",
    "thumb": "https://assets.slotslaunch.com/4656/big-bass-splash.jpg",
    "ProviderName": "Pragmatic Play",
    "ProviderImage": "https://assets.slotslaunch.com/15981/pragmatic-play.png",
    "TypeName": "Slots",
    "ThemeName": "Fish",
    "megaways": 0,
    "bonus_buy": 0,
    "progressive": 0,
    "featured": 0,
    "release": "",
    "reels": "5",
    "rtp": "",
    "volatility": "",
    "paylines": "Fixed",
    "created_at": "2022-06-28T00:17:44.000000Z",
    "updated_at": "2026-01-14T17:23:40.000000Z",
    "published": 1,
    "provider_id": 161,
    "franchise": "Big Bass"
  },
  {
    "name": "Bigger Bass Bonanza",
    "slug": "bigger-bass-bonanza",
    "description": null,
    "url": "https://slotslaunch.com/iframe/5357",
    "thumb": "https://assets.slotslaunch.com/5581/bigger-bass-bonanza.jpg",
    "ProviderName": "Pragmatic Play",
    "ProviderImage": "https://assets.slotslaunch.com/15981/pragmatic-play.png",
    "TypeName": "Slots",
    "ThemeName": "Fish",
    "megaways": 0,
    "bonus_buy": 0,
    "progressive": 0,
    "featured": 0,
    "release": "",
    "reels": "5",
    "rtp": "",
    "volatility": "",
    "paylines": "Fixed",
    "created_at": "2022-01-02T03:13:28.000000Z",
    "updated_at": "2026-01-26T00:01:52.000000Z",
    "published": 1,
    "provider_id": 161,
    "franchise": "Big Bass"
  },
  {
    "name": "Big Bass Floats My Boat",
    "slug": "big-bass-floats-my-boat",
    "description": null,
    "url": "https://slotslaunch.com/iframe/19361",
    "thumb": "https://assets.slotslaunch.com/20007/big-bass-floats-my-boat.jpg",
    "ProviderName": "Pragmatic Play",
    "ProviderImage": "https://assets.slotslaunch.com/15981/pragmatic-play.png",
    "TypeName": "Slots",
    "ThemeName": "Fish",
    "megaways": 0,
    "bonus_buy": 0,
    "progressive": 0,
    "featured": 0,
    "release": "",
    "reels": "",
    "rtp": "",
    "volatility": "",
    "paylines": "",
    "created_at": "2024-01-12T04:20:53.000000Z",
    "updated_at": "2026-01-15T13:51:55.000000Z",
    "published": 1,
    "provider_id": 161,
    "franchise": "Big Bass"
  },
  {
    "name": "Big Bass Amazon Xtreme",
    "slug": "big-bass-amazon-xtreme",
    "description": null,
    "url": "https://slotslaunch.com/iframe/13092",
    "thumb": "https://assets.slotslaunch.com/12449/big-bass-amazon-xtreme.jpg",
    "ProviderName": "Pragmatic Play",
    "ProviderImage": "https://assets.slotslaunch.com/15981/pragmatic-play.png",
    "TypeName": "Slots",
    "ThemeName": "Fish",
    "megaways": 0,
    "bonus_buy": 0,
    "progressive": 0,
    "featured": 0,
    "release": "",
    "reels": "5",
    "rtp": "",
    "volatility": "",
    "paylines": "Fixed",
    "created_at": "2023-05-23T03:08:52.000000Z",
    "updated_at": "2026-01-14T17:24:07.000000Z",
    "published": 1,
    "provider_id": 161,
    "franchise": "Big Bass"
  },
  {
    "name": "Big Bass Hold & Spinner",
    "slug": "big-bass-hold-spinner",
    "description": null,
    "url": "https://slotslaunch.com/iframe/5619",
    "thumb": "https://assets.slotslaunch.com/5842/big-bass-hold-and-spinner.jpg",
    "ProviderName": "Pragmatic Play",
    "ProviderImage": "https://assets.slotslaunch.com/15981/pragmatic-play.png",
    "TypeName": "Slots",
    "ThemeName": "Fish",
    "megaways": 0,
    "bonus_buy": 0,
    "progressive": 0,
    "featured": 0,
    "release": "",
    "reels": "5",
    "rtp": "",
    "volatility": "",
    "paylines": "Fixed",
    "created_at": "2023-02-07T01:40:20.000000Z",
    "updated_at": "2026-01-18T00:01:04.000000Z",
    "published": 1,
    "provider_id": 161,
    "franchise": "Big Bass"
  },
  {
    "name": "Big Bass Boxing Bonus Round",
    "slug": "big-bass-boxing-bonus-round",
    "description": null,
    "url": "https://slotslaunch.com/iframe/35998",
    "thumb": "https://assets.slotslaunch.com/34299/big-bass-boxing-bonus-round.jpg",
    "ProviderName": "Pragmatic Play",
    "ProviderImage": "https://assets.slotslaunch.com/15981/pragmatic-play.png",
    "TypeName": "Slots",
    "ThemeName": "Fish",
    "megaways": 0,
    "bonus_buy": 0,
    "progressive": 0,
    "featured": 0,
    "release": "2025-06-09T05:00:00.000000Z",
    "reels": "5",
    "rtp": "96.5",
    "volatility": "5",
    "paylines": "Fixed",
    "created_at": "2025-05-12T06:02:00.000000Z",
    "updated_at": "2026-01-14T17:24:09.000000Z",
    "published": 1,
    "provider_id": 161,
    "franchise": "Big Bass"
  },
  {
    "name": "Big Bass Halloween",
    "slug": "big-bass-halloween",
    "description": null,
    "url": "https://slotslaunch.com/iframe/16700",
    "thumb": "https://assets.slotslaunch.com/16932/big-bass-halloween.jpg",
    "ProviderName": "Pragmatic Play",
    "ProviderImage": "https://assets.slotslaunch.com/15981/pragmatic-play.png",
    "TypeName": "Slots",
    "ThemeName": "Halloween",
    "megaways": 0,
    "bonus_buy": 0,
    "progressive": 0,
    "featured": 0,
    "release": "",
    "reels": "5",
    "rtp": "",
    "volatility": "",
    "paylines": "Fixed",
    "created_at": "2023-09-22T03:59:34.000000Z",
    "updated_at": "2025-10-03T18:04:12.000000Z",
    "published": 1,
    "provider_id": 161,
    "franchise": "Big Bass"
  },
  {
    "name": "Big Bass Mission Fishin'",
    "slug": "big-bass-mission-fishin",
    "description": null,
    "url": "https://slotslaunch.com/iframe/23541",
    "thumb": "https://assets.slotslaunch.com/23736/big-bass-mission-fishin.jpg",
    "ProviderName": "Pragmatic Play",
    "ProviderImage": "https://assets.slotslaunch.com/15981/pragmatic-play.png",
    "TypeName": "Slots",
    "ThemeName": null,
    "megaways": 0,
    "bonus_buy": 0,
    "progressive": 0,
    "featured": 0,
    "release": "",
    "reels": "5",
    "rtp": "",
    "volatility": "",
    "paylines": "Fixed",
    "created_at": "2024-05-16T02:25:05.000000Z",
    "updated_at": "2026-01-15T13:51:55.000000Z",
    "published": 1,
    "provider_id": 161,
    "franchise": "Big Bass"
  },
  {
    "name": "Sugar Rush",
    "slug": "sugar-rush",
    "description": null,
    "url": "https://slotslaunch.com/iframe/761",
    "thumb": "https://assets.slotslaunch.com/4674/sugar-rush.jpg",
    "ProviderName": "Pragmatic Play",
    "ProviderImage": "https://assets.slotslaunch.com/15981/pragmatic-play.png",
    "TypeName": "Slots",
    "ThemeName": null,
    "megaways": 0,
    "bonus_buy": 0,
    "progressive": 0,
    "featured": 0,
    "release": "",
    "reels": "5",
    "rtp": "",
    "volatility": "",
    "paylines": "Fixed",
    "created_at": "2022-07-04T13:48:03.000000Z",
    "updated_at": "2026-01-14T17:23:42.000000Z",
    "published": 1,
    "provider_id": 161,
    "franchise": "Sugar Rush"
  },
  {
    "name": "Sugar Rush 1000",
    "slug": "sugar-rush-1000",
    "description": null,
    "url": "https://slotslaunch.com/iframe/20070",
    "thumb": "https://assets.slotslaunch.com/22039/sugar-rush-1000.jpg",
    "ProviderName": "Pragmatic Play",
    "ProviderImage": "https://assets.slotslaunch.com/15981/pragmatic-play.png",
    "TypeName": "Slots",
    "ThemeName": "Candy",
    "megaways": 0,
    "bonus_buy": 0,
    "progressive": 0,
    "featured": 0,
    "release": "",
    "reels": "7",
    "rtp": "",
    "volatility": "",
    "paylines": "Fixed",
    "created_at": "2024-02-16T03:46:38.000000Z",
    "updated_at": "2026-01-14T17:23:40.000000Z",
    "published": 1,
    "provider_id": 161,
    "franchise": "Sugar Rush"
  },
  {
    "name": "Sugar Supreme Powernudge",
    "slug": "sugar-supreme-powernudge",
    "description": null,
    "url": "https://slotslaunch.com/iframe/16703",
    "thumb": "https://assets.slotslaunch.com/16946/sugar-supreme-powernudge.jpg",
    "ProviderName": "Pragmatic Play",
    "ProviderImage": "https://assets.slotslaunch.com/15981/pragmatic-play.png",
    "TypeName": "Slots",
    "ThemeName": null,
    "megaways": 0,
    "bonus_buy": 0,
    "progressive": 0,
    "featured": 0,
    "release": "",
    "reels": "6",
    "rtp": "",
    "volatility": "",
    "paylines": "Fixed",
    "created_at": "2023-09-29T05:46:31.000000Z",
    "updated_at": "2026-01-15T22:45:32.000000Z",
    "published": 1,
    "provider_id": 161,
    "franchise": "Sugar Rush"
  },
  {
    "name": "Wolf Gold",
    "slug": "wolf-gold",
    "description": null,
    "url": "https://slotslaunch.com/iframe/5516",
    "thumb": "https://assets.slotslaunch.com/5739/wolf-gold.jpg",
    "ProviderName": "Pragmatic Play",
    "ProviderImage": "https://assets.slotslaunch.com/15981/pragmatic-play.png",
    "TypeName": "Slots",
    "ThemeName": "Wolf",
    "megaways": 0,
    "bonus_buy": 0,
    "progressive": 1,
    "featured": 0,
    "release": "",
    "reels": "5",
    "rtp": "",
    "volatility": "",
    "paylines": "Fixed",
    "created_at": "2022-01-02T03:13:28.000000Z",
    "updated_at": "2025-09-29T15:49:25.000000Z",
    "published": 1,
    "provider_id": 161,
    "franchise": "Wolf Gold"
  },
  {
    "name": "Wolf Gold Ultimate",
    "slug": "wolf-gold-ultimate",
    "description": null,
    "url": "https://slotslaunch.com/iframe/31269",
    "thumb": "https://assets.slotslaunch.com/28692/wolf-gold-ultimate.jpg",
    "ProviderName": "Pragmatic Play",
    "ProviderImage": "https://assets.slotslaunch.com/15981/pragmatic-play.png",
    "TypeName": "Slots",
    "ThemeName": "Wild West",
    "megaways": 0,
    "bonus_buy": 0,
    "progressive": 0,
    "featured": 0,
    "release": "2024-11-07T06:00:00.000000Z",
    "reels": "5",
    "rtp": "95.56",
    "volatility": "3",
    "paylines": "Fixed",
    "created_at": "2024-10-04T05:24:00.000000Z",
    "updated_at": "2025-10-05T13:56:58.000000Z",
    "published": 1,
    "provider_id": 161,
    "franchise": "Wolf Gold"
  },
  {
    "name": "Buffalo King Megaways",
    "slug": "buffalo-king-megaways",
    "description": null,
    "url": "https://slotslaunch.com/iframe/3391",
    "thumb": "https://assets.slotslaunch.com/2731/buffal-king-megaways.jpg",
    "ProviderName": "Pragmatic Play",
    "ProviderImage": "https://assets.slotslaunch.com/15981/pragmatic-play.png",
    "TypeName": "Slots",
    "ThemeName": "Buffalo",
    "megaways": 1,
    "bonus_buy": 0,
    "progressive": 0,
    "featured": 0,
    "release": "",
    "reels": "7",
    "rtp": "",
    "volatility": "",
    "paylines": "Fixed",
    "created_at": "2022-01-01T18:01:00.000000Z",
    "updated_at": "2026-01-14T17:24:07.000000Z",
    "published": 1,
    "provider_id": 161,
    "franchise": "Buffalo King"
  },
  {
    "name": "Buffalo King Untamed Megaways",
    "slug": "buffalo-king-untamed-megaways",
    "description": null,
    "url": "https://slotslaunch.com/iframe/23542",
    "thumb": "https://assets.slotslaunch.com/24658/buffalo-king-untamed-megaways.jpg",
    "ProviderName": "Pragmatic Play",
    "ProviderImage": "https://assets.slotslaunch.com/15981/pragmatic-play.png",
    "TypeName": "Slots",
    "ThemeName": null,
    "megaways": 1,
    "bonus_buy": 0,
    "progressive": 0,
    "featured": 0,
    "release": "",
    "reels": "6",
    "rtp": "",
    "volatility": "",
    "paylines": "Fixed",
    "created_at": "2024-05-23T04:25:23.000000Z",
    "updated_at": "2025-10-04T20:31:24.000000Z",
    "published": 1,
    "provider_id": 161,
    "franchise": "Buffalo King"
  },
  {
    "name": "The Dog House Megaways",
    "slug": "the-dog-house-megaways",
    "description": null,
    "url": "https://slotslaunch.com/iframe/3328",
    "thumb": "https://assets.slotslaunch.com/2667/the-dog-house-megaways.jpg",
    "ProviderName": "Pragmatic Play",
    "ProviderImage": "https://assets.slotslaunch.com/15981/pragmatic-play.png",
    "TypeName": "Slots",
    "ThemeName": "Animal",
    "megaways": 1,
    "bonus_buy": 0,
    "progressive": 0,
    "featured": 0,
    "release": "",
    "reels": "6",
    "rtp": "",
    "volatility": "",
    "paylines": "Fixed",
    "created_at": "2022-01-01T18:01:00.000000Z",
    "updated_at": "2026-01-14T17:24:07.000000Z",
    "published": 1,
    "provider_id": 161,
    "franchise": "The Dog House"
  },
  {
    "name": "The Dog House Multihold",
    "slug": "the-dog-house-multihold",
    "description": null,
    "url": "https://slotslaunch.com/iframe/4595",
    "thumb": "https://assets.slotslaunch.com/5151/the-dog-house-multihold.jpg",
    "ProviderName": "Pragmatic Play",
    "ProviderImage": "https://assets.slotslaunch.com/15981/pragmatic-play.png",
    "TypeName": "Slots",
    "ThemeName": "Animal",
    "megaways": 0,
    "bonus_buy": 0,
    "progressive": 0,
    "featured": 0,
    "release": "",
    "reels": "5",
    "rtp": "",
    "volatility": "",
    "paylines": "Fixed",
    "created_at": "2023-01-26T22:07:43.000000Z",
    "updated_at": "2025-10-02T20:09:06.000000Z",
    "published": 1,
    "provider_id": 161,
    "franchise": "The Dog House"
  },
  {
    "name": "The Dog House - Royal Hunt",
    "slug": "the-dog-house-royal-hunt",
    "description": null,
    "url": "https://slotslaunch.com/iframe/34040",
    "thumb": "https://assets.slotslaunch.com/31730/the-dog-house-royal-hunt.jpg",
    "ProviderName": "Pragmatic Play",
    "ProviderImage": "https://assets.slotslaunch.com/15981/pragmatic-play.png",
    "TypeName": "Slots",
    "ThemeName": "Adventure",
    "megaways": 0,
    "bonus_buy": 0,
    "progressive": 0,
    "featured": 0,
    "release": "2025-03-31T05:00:00.000000Z",
    "reels": "5",
    "rtp": "95.5",
    "volatility": "5",
    "paylines": "Fixed",
    "created_at": "2025-03-03T06:20:00.000000Z",
    "updated_at": "2026-01-14T17:24:07.000000Z",
    "published": 1,
    "provider_id": 161,
    "franchise": "The Dog House"
  },
  {
    "name": "Fruit Party",
    "slug": "fruit-party",
    "description": null,
    "url": "https://slotslaunch.com/iframe/5394",
    "thumb": "https://assets.slotslaunch.com/5618/fruit-party.jpg",
    "ProviderName": "Pragmatic Play",
    "ProviderImage": "https://assets.slotslaunch.com/15981/pragmatic-play.png",
    "TypeName": "Slots",
    "ThemeName": "Fruit",
    "megaways": 0,
    "bonus_buy": 0,
    "progressive": 0,
    "featured": 0,
    "release": "",
    "reels": "7",
    "rtp": "",
    "volatility": "",
    "paylines": "Fixed",
    "created_at": "2022-01-02T03:13:28.000000Z",
    "updated_at": "2026-01-16T00:01:13.000000Z",
    "published": 1,
    "provider_id": 161,
    "franchise": "Fruit Party"
  },
  {
    "name": "Fruit Party 2",
    "slug": "fruit-party-2",
    "description": null,
    "url": "https://slotslaunch.com/iframe/5395",
    "thumb": "https://assets.slotslaunch.com/5619/fruit-party-2.jpg",
    "ProviderName": "Pragmatic Play",
    "ProviderImage": "https://assets.slotslaunch.com/15981/pragmatic-play.png",
    "TypeName": "Slots",
    "ThemeName": "Fruit",
    "megaways": 0,
    "bonus_buy": 0,
    "progressive": 0,
    "featured": 0,
    "release": "",
    "reels": "7",
    "rtp": "",
    "volatility": "",
    "paylines": "Fixed",
    "created_at": "2022-01-02T03:13:28.000000Z",
    "updated_at": "2025-09-26T22:52:45.000000Z",
    "published": 1,
    "provider_id": 161,
    "franchise": "Fruit Party"
  },
  {
    "name": "Madame Destiny Megaways",
    "slug": "madame-destiny-megaways",
    "description": null,
    "url": "https://slotslaunch.com/iframe/3302",
    "thumb": "https://assets.slotslaunch.com/2641/madame-destiny-megaways.jpg",
    "ProviderName": "Pragmatic Play",
    "ProviderImage": "https://assets.slotslaunch.com/15981/pragmatic-play.png",
    "TypeName": "Slots",
    "ThemeName": "Halloween",
    "megaways": 1,
    "bonus_buy": 0,
    "progressive": 0,
    "featured": 0,
    "release": "",
    "reels": "7",
    "rtp": "",
    "volatility": "",
    "paylines": "Fixed",
    "created_at": "2022-01-01T18:01:00.000000Z",
    "updated_at": "2026-01-15T22:45:32.000000Z",
    "published": 1,
    "provider_id": 161,
    "franchise": "Madame Destiny"
  },
  {
    "name": "Mustang Gold",
    "slug": "mustang-gold",
    "description": null,
    "url": "https://slotslaunch.com/iframe/5449",
    "thumb": "https://assets.slotslaunch.com/5672/mustang-gold.jpg",
    "ProviderName": "Pragmatic Play",
    "ProviderImage": "https://assets.slotslaunch.com/15981/pragmatic-play.png",
    "TypeName": "Slots",
    "ThemeName": null,
    "megaways": 0,
    "bonus_buy": 0,
    "progressive": 1,
    "featured": 0,
    "release": "",
    "reels": "5",
    "rtp": "",
    "volatility": "",
    "paylines": "Fixed",
    "created_at": "2022-01-02T03:13:28.000000Z",
    "updated_at": "2025-09-27T23:12:45.000000Z",
    "published": 1,
    "provider_id": 161,
    "franchise": "Mustang"
  },
  {
    "name": "Great Rhino Megaways",
    "slug": "great-rhino-megaways",
    "description": null,
    "url": "https://slotslaunch.com/iframe/3288",
    "thumb": "https://assets.slotslaunch.com/2627/great-rhino-megaways.jpg",
    "ProviderName": "Pragmatic Play",
    "ProviderImage": "https://assets.slotslaunch.com/15981/pragmatic-play.png",
    "TypeName": "Slots",
    "ThemeName": "Nature",
    "megaways": 1,
    "bonus_buy": 0,
    "progressive": 0,
    "featured": 0,
    "release": "",
    "reels": "8",
    "rtp": "",
    "volatility": "",
    "paylines": "Fixed",
    "created_at": "2022-01-01T18:01:00.000000Z",
    "updated_at": "2026-01-01T16:06:40.000000Z",
    "published": 1,
    "provider_id": 161,
    "franchise": "Great Rhino"
  },
  {
    "name": "The Hand of Midas",
    "slug": "the-hand-of-midas",
    "description": null,
    "url": "https://slotslaunch.com/iframe/5492",
    "thumb": "https://assets.slotslaunch.com/5715/the-hand-of-midas.jpg",
    "ProviderName": "Pragmatic Play",
    "ProviderImage": "https://assets.slotslaunch.com/15981/pragmatic-play.png",
    "TypeName": "Slots",
    "ThemeName": null,
    "megaways": 0,
    "bonus_buy": 0,
    "progressive": 0,
    "featured": 0,
    "release": "",
    "reels": "5",
    "rtp": "",
    "volatility": "",
    "paylines": "Fixed",
    "created_at": "2022-01-02T03:13:28.000000Z",
    "updated_at": "2025-09-29T06:03:29.000000Z",
    "published": 1,
    "provider_id": 161,
    "franchise": "Hand of Midas"
  },
  {
    "name": "Zeus vs Hades Gods of War",
    "slug": "zeus-vs-hades-gods-of-war",
    "description": null,
    "url": "https://slotslaunch.com/iframe/9547",
    "thumb": "https://assets.slotslaunch.com/11469/zeus-vs-hades-gods-of-war.jpg",
    "ProviderName": "Pragmatic Play",
    "ProviderImage": "https://assets.slotslaunch.com/15981/pragmatic-play.png",
    "TypeName": "Slots",
    "ThemeName": null,
    "megaways": 0,
    "bonus_buy": 0,
    "progressive": 0,
    "featured": 0,
    "release": "",
    "reels": "5",
    "rtp": "",
    "volatility": "",
    "paylines": "Fixed",
    "created_at": "2023-04-25T01:45:55.000000Z",
    "updated_at": "2026-01-14T17:23:40.000000Z",
    "published": 1,
    "provider_id": 161,
    "franchise": "Zeus / Gods"
  },
  {
    "name": "Starlight Princess",
    "slug": "starlight-princess",
    "description": null,
    "url": "https://slotslaunch.com/iframe/5478",
    "thumb": "https://assets.slotslaunch.com/5701/starlight-princess.jpg",
    "ProviderName": "Pragmatic Play",
    "ProviderImage": "https://assets.slotslaunch.com/15981/pragmatic-play.png",
    "TypeName": "Slots",
    "ThemeName": "Princess",
    "megaways": 0,
    "bonus_buy": 0,
    "progressive": 0,
    "featured": 0,
    "release": "",
    "reels": "6",
    "rtp": "",
    "volatility": "",
    "paylines": "Fixed",
    "created_at": "2022-01-02T03:13:28.000000Z",
    "updated_at": "2026-01-18T00:01:04.000000Z",
    "published": 1,
    "provider_id": 161,
    "franchise": "Starlight Princess"
  },
  {
    "name": "Starlight Princess 1000",
    "slug": "starlight-princess-1000",
    "description": null,
    "url": "https://slotslaunch.com/iframe/15726",
    "thumb": "https://assets.slotslaunch.com/15454/starlight-princess-1000.jpg",
    "ProviderName": "Pragmatic Play",
    "ProviderImage": "https://assets.slotslaunch.com/15981/pragmatic-play.png",
    "TypeName": "Slots",
    "ThemeName": "Princess",
    "megaways": 0,
    "bonus_buy": 0,
    "progressive": 0,
    "featured": 0,
    "release": "",
    "reels": "6",
    "rtp": "",
    "volatility": "",
    "paylines": "Fixed",
    "created_at": "2023-07-25T01:40:26.000000Z",
    "updated_at": "2026-01-14T17:23:42.000000Z",
    "published": 1,
    "provider_id": 161,
    "franchise": "Starlight Princess"
  },
  {
    "name": "Fire Strike",
    "slug": "fire-strike",
    "description": null,
    "url": "https://slotslaunch.com/iframe/5391",
    "thumb": "https://assets.slotslaunch.com/5615/fire-strike.jpg",
    "ProviderName": "Pragmatic Play",
    "ProviderImage": "https://assets.slotslaunch.com/15981/pragmatic-play.png",
    "TypeName": "Slots",
    "ThemeName": null,
    "megaways": 0,
    "bonus_buy": 0,
    "progressive": 0,
    "featured": 0,
    "release": "",
    "reels": "5",
    "rtp": "",
    "volatility": "",
    "paylines": "Fixed",
    "created_at": "2022-01-02T03:13:28.000000Z",
    "updated_at": "2025-09-26T21:13:56.000000Z",
    "published": 1,
    "provider_id": 161,
    "franchise": "Fire Strike"
  },
  {
    "name": "Fire Strike 2",
    "slug": "fire-strike-2",
    "description": null,
    "url": "https://slotslaunch.com/iframe/753",
    "thumb": "https://assets.slotslaunch.com/4667/fire-strike-2.jpg",
    "ProviderName": "Pragmatic Play",
    "ProviderImage": "https://assets.slotslaunch.com/15981/pragmatic-play.png",
    "TypeName": "Slots",
    "ThemeName": "Fruit",
    "megaways": 0,
    "bonus_buy": 0,
    "progressive": 0,
    "featured": 0,
    "release": "",
    "reels": "",
    "rtp": "",
    "volatility": "",
    "paylines": "",
    "created_at": "2022-07-20T12:08:09.000000Z",
    "updated_at": "2025-10-01T23:59:15.000000Z",
    "published": 1,
    "provider_id": 161,
    "franchise": "Fire Strike"
  },
  {
    "name": "Chicken Chase",
    "slug": "chicken-chase",
    "description": null,
    "url": "https://slotslaunch.com/iframe/747",
    "thumb": "https://assets.slotslaunch.com/4661/chicken-chase.jpg",
    "ProviderName": "Pragmatic Play",
    "ProviderImage": "https://assets.slotslaunch.com/15981/pragmatic-play.png",
    "TypeName": "Slots",
    "ThemeName": null,
    "megaways": 0,
    "bonus_buy": 0,
    "progressive": 0,
    "featured": 0,
    "release": "",
    "reels": "5",
    "rtp": "",
    "volatility": "",
    "paylines": "Fixed",
    "created_at": "2022-07-05T21:27:49.000000Z",
    "updated_at": "2025-10-01T20:57:56.000000Z",
    "published": 1,
    "provider_id": 161,
    "franchise": "Chicken Chase"
  },
  {
    "name": "John Hunter and the Tomb of the Scarab Queen",
    "slug": "john-hunter-and-the-tomb-of-the-scarab-queen",
    "description": null,
    "url": "https://slotslaunch.com/iframe/5424",
    "thumb": "https://assets.slotslaunch.com/5648/john-hunter-and-the-tomb-of-the-scarab-queen.jpg",
    "ProviderName": "Pragmatic Play",
    "ProviderImage": "https://assets.slotslaunch.com/15981/pragmatic-play.png",
    "TypeName": "Slots",
    "ThemeName": null,
    "megaways": 0,
    "bonus_buy": 0,
    "progressive": 0,
    "featured": 0,
    "release": "",
    "reels": "5",
    "rtp": "",
    "volatility": "",
    "paylines": "Fixed",
    "created_at": "2022-01-02T03:13:28.000000Z",
    "updated_at": "2025-09-27T11:23:03.000000Z",
    "published": 1,
    "provider_id": 161,
    "franchise": "John Hunter"
  },
  {
    "name": "John Hunter and the Book of Tut",
    "slug": "john-hunter-and-the-book-of-tut",
    "description": null,
    "url": "https://slotslaunch.com/iframe/5420",
    "thumb": "https://assets.slotslaunch.com/5644/john-hunter-and-the-book-of-tut.jpg",
    "ProviderName": "Pragmatic Play",
    "ProviderImage": "https://assets.slotslaunch.com/15981/pragmatic-play.png",
    "TypeName": "Slots",
    "ThemeName": "Book of",
    "megaways": 0,
    "bonus_buy": 0,
    "progressive": 0,
    "featured": 0,
    "release": "",
    "reels": "5",
    "rtp": "",
    "volatility": "",
    "paylines": "Fixed",
    "created_at": "2022-01-02T03:13:28.000000Z",
    "updated_at": "2025-09-27T09:31:17.000000Z",
    "published": 1,
    "provider_id": 161,
    "franchise": "John Hunter"
  },
  {
    "name": "Aztec Gems",
    "slug": "aztec-gems",
    "description": null,
    "url": "https://slotslaunch.com/iframe/5353",
    "thumb": "https://assets.slotslaunch.com/5577/aztec-gems.jpg",
    "ProviderName": "Pragmatic Play",
    "ProviderImage": "https://assets.slotslaunch.com/15981/pragmatic-play.png",
    "TypeName": "Slots",
    "ThemeName": "Aztec",
    "megaways": 0,
    "bonus_buy": 0,
    "progressive": 0,
    "featured": 0,
    "release": "",
    "reels": "4",
    "rtp": "",
    "volatility": "",
    "paylines": "Fixed",
    "created_at": "2022-01-02T03:13:28.000000Z",
    "updated_at": "2025-10-01T05:06:06.000000Z",
    "published": 1,
    "provider_id": 161,
    "franchise": "Aztec Gems"
  },
  {
    "name": "Aztec Gems Deluxe",
    "slug": "aztec-gems-deluxe",
    "description": null,
    "url": "https://slotslaunch.com/iframe/5354",
    "thumb": "https://assets.slotslaunch.com/5578/aztec-gems-deluxe.jpg",
    "ProviderName": "Pragmatic Play",
    "ProviderImage": "https://assets.slotslaunch.com/15981/pragmatic-play.png",
    "TypeName": "Slots",
    "ThemeName": "Aztec",
    "megaways": 0,
    "bonus_buy": 0,
    "progressive": 1,
    "featured": 0,
    "release": "",
    "reels": "3",
    "rtp": "",
    "volatility": "",
    "paylines": "Fixed",
    "created_at": "2022-01-02T03:13:28.000000Z",
    "updated_at": "2025-10-01T05:31:27.000000Z",
    "published": 1,
    "provider_id": 161,
    "franchise": "Aztec Gems"
  },
  {
    "name": "5 Lions Megaways",
    "slug": "5-lions-megaways",
    "description": null,
    "url": "https://slotslaunch.com/iframe/3280",
    "thumb": "https://assets.slotslaunch.com/2619/5-lions-megaways.jpg",
    "ProviderName": "Pragmatic Play",
    "ProviderImage": "https://assets.slotslaunch.com/15981/pragmatic-play.png",
    "TypeName": "Slots",
    "ThemeName": "Asian",
    "megaways": 1,
    "bonus_buy": 0,
    "progressive": 0,
    "featured": 0,
    "release": "",
    "reels": "6",
    "rtp": "",
    "volatility": "",
    "paylines": "Fixed",
    "created_at": "2022-01-01T18:01:00.000000Z",
    "updated_at": "2026-01-14T17:24:07.000000Z",
    "published": 1,
    "provider_id": 161,
    "franchise": "5 Lions"
  },
  {
    "name": "5 Lions Dance",
    "slug": "5-lions-dance",
    "description": null,
    "url": "https://slotslaunch.com/iframe/5340",
    "thumb": "https://assets.slotslaunch.com/5564/5-lions-dance.jpg",
    "ProviderName": "Pragmatic Play",
    "ProviderImage": "https://assets.slotslaunch.com/15981/pragmatic-play.png",
    "TypeName": "Slots",
    "ThemeName": "Asian",
    "megaways": 0,
    "bonus_buy": 0,
    "progressive": 0,
    "featured": 0,
    "release": "",
    "reels": "5",
    "rtp": "",
    "volatility": "",
    "paylines": "Fixed",
    "created_at": "2022-01-02T03:13:28.000000Z",
    "updated_at": "2025-10-01T00:06:54.000000Z",
    "published": 1,
    "provider_id": 161,
    "franchise": "5 Lions"
  },
  {
    "name": "Christmas Carol Megaways",
    "slug": "christmas-carol-megaways",
    "description": null,
    "url": "https://slotslaunch.com/iframe/3283",
    "thumb": "https://assets.slotslaunch.com/2622/christmas-carol-megaways.jpg",
    "ProviderName": "Pragmatic Play",
    "ProviderImage": "https://assets.slotslaunch.com/15981/pragmatic-play.png",
    "TypeName": "Slots",
    "ThemeName": "Christmas",
    "megaways": 1,
    "bonus_buy": 0,
    "progressive": 0,
    "featured": 0,
    "release": "",
    "reels": "7",
    "rtp": "",
    "volatility": "",
    "paylines": "Fixed",
    "created_at": "2022-01-01T18:01:00.000000Z",
    "updated_at": "2026-01-01T16:06:40.000000Z",
    "published": 1,
    "provider_id": 161,
    "franchise": "Christmas Carol"
  },
  {
    "name": "Candy Village",
    "slug": "candy-village",
    "description": null,
    "url": "https://slotslaunch.com/iframe/16559",
    "thumb": "https://assets.slotslaunch.com/16212/candy-village.jpg",
    "ProviderName": "Pragmatic Play",
    "ProviderImage": "https://assets.slotslaunch.com/15981/pragmatic-play.png",
    "TypeName": "Slots",
    "ThemeName": "Candy",
    "megaways": 0,
    "bonus_buy": 0,
    "progressive": 0,
    "featured": 0,
    "release": "",
    "reels": "6",
    "rtp": "",
    "volatility": "",
    "paylines": "Fixed",
    "created_at": "2022-01-01T18:01:00.000000Z",
    "updated_at": "2025-09-25T12:56:19.000000Z",
    "published": 1,
    "provider_id": 161,
    "franchise": "Candy"
  },
  {
    "name": "Chilli Heat",
    "slug": "chilli-heat",
    "description": null,
    "url": "https://slotslaunch.com/iframe/5369",
    "thumb": "https://assets.slotslaunch.com/5593/chilli-heat.jpg",
    "ProviderName": "Pragmatic Play",
    "ProviderImage": "https://assets.slotslaunch.com/15981/pragmatic-play.png",
    "TypeName": "Slots",
    "ThemeName": null,
    "megaways": 0,
    "bonus_buy": 0,
    "progressive": 1,
    "featured": 0,
    "release": "",
    "reels": "5",
    "rtp": "",
    "volatility": "",
    "paylines": "Fixed",
    "created_at": "2022-01-02T03:13:28.000000Z",
    "updated_at": "2026-01-17T00:00:36.000000Z",
    "published": 1,
    "provider_id": 161,
    "franchise": "Chilli Heat"
  },
  {
    "name": "Chilli Heat Megaways",
    "slug": "chilli-heat-megaways",
    "description": null,
    "url": "https://slotslaunch.com/iframe/3282",
    "thumb": "https://assets.slotslaunch.com/2621/chilli-heat-megaways.jpg",
    "ProviderName": "Pragmatic Play",
    "ProviderImage": "https://assets.slotslaunch.com/15981/pragmatic-play.png",
    "TypeName": "Slots",
    "ThemeName": null,
    "megaways": 1,
    "bonus_buy": 0,
    "progressive": 0,
    "featured": 0,
    "release": "",
    "reels": "6",
    "rtp": "",
    "volatility": "",
    "paylines": "Fixed",
    "created_at": "2022-01-01T18:01:00.000000Z",
    "updated_at": "2026-01-01T16:06:40.000000Z",
    "published": 1,
    "provider_id": 161,
    "franchise": "Chilli Heat"
  }
]